{"Clicks of partners per day":{"C0F515F0A2D0A5D9F854008BA76EB537":[464,751,105,604,0,768,775,877,894,791,629,760,939,912,690,757,732,679,772,710,749,518,676,678,633,965,918,954,933,938,707,599,753,449,0,0,0,0,0,0]},"Sales of partners per day":{"C0F515F0A2D0A5D9F854008BA76EB537":[140.45228999999998,657.18633,126.16814,462.48985,0.0,509.92772,692.14275,696.3072099999999,708.6495400000001,558.2426600000001,454.72469,581.26874,697.98606,624.5710899999999,427.3841800000001,527.07657,544.15171,708.1007100000002,721.1429700000001,668.5063700000001,693.8217300000001,819.61871,330.92275,647.88175,703.23927,792.4120400000003,840.6717900000001,602.6268899999999,590.28619,447.88262000000003,737.87351,281.30129,312.31003999999996,189.07718999999997,0.0,0.0,0.0,0.0,0.0,0.0]},"Clicks sum without exclusion":{"C0F515F0A2D0A5D9F854008BA76EB537":24079},"Sales sum without exclusion":{"C0F515F0A2D0A5D9F854008BA76EB537":18496.405350000005},"Gain info per partner per day":{"C0F515F0A2D0A5D9F854008BA76EB537":[{"clicks_savings":0,"sale_losses":0,"profit_losses":0,"profit_gain":0},{"clicks_savings":3,"sale_losses":0.0,"profit_losses":0.0,"profit_gain":-3.0},{"clicks_savings":1,"sale_losses":0.0,"profit_losses":0.0,"profit_gain":-1.0},{"clicks_savings":1,"sale_losses":0.0,"profit_losses":0.0,"profit_gain":-1.0},{"clicks_savings":3,"sale_losses":0.0,"profit_losses":0.0,"profit_gain":-3.0},{"clicks_savings":12,"sale_losses":44.90712,"profit_losses":4.490711999999999,"profit_gain":-2.1204336},{"clicks_savings":8,"sale_losses":0.0,"profit_losses":0.0,"profit_gain":-8.0},{"clicks_savings":0,"sale_losses":0,"profit_losses":0,"profit_gain":0},{"clicks_savings":9,"sale_losses":4.86216,"profit_losses":0.486216,"profit_gain":-7.9303248},{"clicks_savings":7,"sale_losses":0.0,"profit_losses":0.0,"profit_gain":-7.0},{"clicks_savings":8,"sale_losses":21.075670000000002,"profit_losses":2.1075670000000004,"profit_gain":-3.3633526},{"clicks_savings":3,"sale_losses":0.0,"profit_losses":0.0,"profit_gain":-3.0},{"clicks_savings":1,"sale_losses":0.0,"profit_losses":0.0,"profit_gain":-1.0},{"clicks_savings":2,"sale_losses":0.0,"profit_losses":0.0,"profit_gain":-2.0},{"clicks_savings":8,"sale_losses":0.0,"profit_losses":0.0,"profit_gain":-8.0},{"clicks_savings":0,"sale_losses":0,"profit_losses":0,"profit_gain":0},{"clicks_savings":3,"sale_losses":0.0,"profit_losses":0.0,"profit_gain":-3.0},{"clicks_savings":0,"sale_losses":0,"profit_losses":0,"profit_gain":0},{"clicks_savings":7,"sale_losses":22.265710000000002,"profit_losses":2.2265710000000003,"profit_gain":-2.101543799999999},{"clicks_savings":1,"sale_losses":0.0,"profit_losses":0.0,"profit_gain":-1.0},{"clicks_savings":0,"sale_losses":0,"profit_losses":0,"profit_gain":0},{"clicks_savings":1,"sale_losses":0.0,"profit_losses":0.0,"profit_gain":-1.0},{"clicks_savings":1,"sale_losses":0.0,"profit_losses":0.0,"profit_gain":-1.0},{"clicks_savings":3,"sale_losses":0.0,"profit_losses":0.0,"profit_gain":-3.0},{"clicks_savings":10,"sale_losses":0.0,"profit_losses":0.0,"profit_gain":-10.0},{"clicks_savings":8,"sale_losses":0.0,"profit_losses":0.0,"profit_gain":-8.0},{"clicks_savings":4,"sale_losses":0.0,"profit_losses":0.0,"profit_gain":-4.0},{"clicks_savings":2,"sale_losses":0.0,"profit_losses":0.0,"profit_gain":-2.0},{"clicks_savings":10,"sale_losses":5.22041,"profit_losses":0.5220410000000001,"profit_gain":-8.8515098},{"clicks_savings":4,"sale_losses":0.0,"profit_losses":0.0,"profit_gain":-4.0},{"clicks_savings":1,"sale_losses":0.0,"profit_losses":0.0,"profit_gain":-1.0},{"clicks_savings":2,"sale_losses":3.1312,"profit_losses":0.31312,"profit_gain":-1.3111359999999999},{"clicks_savings":1,"sale_losses":0.0,"profit_losses":0.0,"profit_gain":-1.0}]},"Gain info summed":{"clicks_savings":124,"sale_losses":101.46227000000002,"profit_losses":10.146227,"profit_gain":-101.6783006}}